novosparc/__init__.py
novosparc/analysis/__init__.py
novosparc/analysis/_analysis.py
novosparc/common/__init__.py
novosparc/common/_tissue.py
novosparc/geometry/__init__.py
novosparc/geometry/_geometry.py
novosparc/io/__init__.py
novosparc/io/_data_loading.py
novosparc/io/_saving.py
novosparc/plotting/__init__.py
novosparc/plotting/_plotting.py
novosparc/preprocessing/__init__.py
novosparc/preprocessing/_preprocessing.py
novosparc/reconstruction/_GWadjusted.py
novosparc/reconstruction/__init__.py
novosparc/reconstruction/_reconstruction.py
novosparc-0.4.4.dist-info/LICENSE
novosparc-0.4.4.dist-info/METADATA
novosparc-0.4.4.dist-info/WHEEL
novosparc-0.4.4.dist-info/top_level.txt
novosparc-0.4.4.dist-info/RECORD
