Metadata-Version: 2.1
Name: novosparc
Version: 0.4.4
Summary: De novo spatial reconstruction of single-cell gene expression.
Home-page: https://github.com/rajewsky-lab/novosparc
Author: Nikos Karaiskos, Mor Nitzan, Enes Senel, Noa Moriel
Author-email: nikolaos.karaiskos@mdc-berlin.de, mornitzan@fas.harvard.edu, enes.senel@mdc-berlin.de, noa.moriel@mail.huji.ac.il
License: MIT
Platform: UNKNOWN
Classifier: Programming Language :: Python :: 3
Classifier: Operating System :: POSIX :: Linux
Classifier: Operating System :: MacOS :: MacOS X
Requires-Dist: POT (>=0.7.0)
Requires-Dist: numpy
Requires-Dist: anndata (>=0.7.5)
Requires-Dist: matplotlib (>=3.3.2)
Requires-Dist: scipy
Requires-Dist: pandas
Requires-Dist: recommonmark
Requires-Dist: scanpy (>=1.6.0)
Requires-Dist: scikit-learn
